Metadata-Version: 1.0
Name: simangadistribution
Version: 1.3
Summary: Gaussian distribution
Home-page: UNKNOWN
Author: UNKNOWN
Author-email: UNKNOWN
License: UNKNOWN
Platform: UNKNOWN
